examples/__init__.py
examples/like_tweet.py
examples/sample_streaming.py
examples/search_streaming.py
pytwitter/__init__.py
pytwitter/api.py
pytwitter/error.py
pytwitter/rate_limit.py
pytwitter/streaming.py
pytwitter/models/__init__.py
pytwitter/models/base.py
pytwitter/models/compliance.py
pytwitter/models/dm_event.py
pytwitter/models/ext.py
pytwitter/models/list.py
pytwitter/models/media.py
pytwitter/models/media_upload.py
pytwitter/models/place.py
pytwitter/models/poll.py
pytwitter/models/space.py
pytwitter/models/stream.py
pytwitter/models/tweet.py
pytwitter/models/usage.py
pytwitter/models/user.py
pytwitter/utils/__init__.py
pytwitter/utils/convertors.py
pytwitter/utils/validators.py
tests/__init__.py
tests/conftest.py
tests/test_models.py
tests/test_rate_limit.py
tests/test_response.py
tests/test_utils.py
tests/apis/__init__.py
tests/apis/test_auth.py
tests/apis/test_compliance_job.py
tests/apis/test_dm_events.py
tests/apis/test_follows.py
tests/apis/test_hidden_reply.py
tests/apis/test_lists.py
tests/apis/test_media_upload.py
tests/apis/test_search.py
tests/apis/test_space.py
tests/apis/test_timelines.py
tests/apis/test_tweets.py
tests/apis/test_usage.py
tests/apis/test_users.py
tests/streams/__init__.py
tests/streams/test_auth.py
tests/streams/test_rules.py
tests/streams/test_stream.py
python_twitter_pro-0.2.5.dist-info/LICENSE
python_twitter_pro-0.2.5.dist-info/METADATA
python_twitter_pro-0.2.5.dist-info/WHEEL
python_twitter_pro-0.2.5.dist-info/top_level.txt
python_twitter_pro-0.2.5.dist-info/RECORD
